Workbook

Sheet Assumptions
A1: Item | B1: Value | C1: Unit | D1: Source or note
A2: Model | B2: gemini-3.5-flash-lite | D2: Prototype model, chosen for speed and cost
A3: Input price per 1M tokens | B3: 0.3 | C3: USD | D3: Google Gemini API pricing page, Oct 2026
A4: Output price per 1M tokens | B4: 2.5 | C4: USD | D4: Google Gemini API pricing page, Oct 2026
A5: Exchange rate | B5: 90 | C5: INR per USD | D5: Assumption, update before submitting
A6: Average input tokens per message | B6: 2200 | C6: tokens | D6: Measured in S1 test run: 19,974 input tokens over 9 calls
A7: Average output tokens per message | B7: 200 | C7: tokens | D7: Measured in S1 test run: 1,831 output tokens over 9 calls
A8: Orders per business per month | B8: 100 | C8: orders | D8: Assumption: a bakery with helpers takes 20 to 30 orders a week
A9: Messages per order reaching the model | B9: 12 | C9: messages | D9: Assumption
A10: Extra non-order messages | B10: 0.3 | C10: share | D10: Assumption: small talk and enquiries that never become orders
A11: Usage stress multiplier | B11: 3 | C11: x | D11: Stress test for long chats, images and retries
A12: Hosting and database, 100 businesses | B12: 45 | C12: USD per month | D12: Vercel and Supabase paid plans, to verify
A13: Hosting and database, 1,000 businesses | B13: 200 | C13: USD per month | D13: Assumption
A14: Price hypothesis, low | B14: 499 | C14: INR per month | D14: To validate in beta
A15: Price hypothesis, high | B15: 999 | C15: INR per month | D15: To validate in beta

Sheet Usage and AI cost
A1: Metric | B1: USD | C1: INR
A2: Cost per message | B2: =(Assumptions!B6*Assumptions!B3+Assumptions!B7*Assumptions!B4)/1000000 -> 0.00116 | C2: =B2*Assumptions!$B$5 -> 0.1044
A3: Cost per order | B3: =B2*Assumptions!B9 -> 0.01392 | C3: =B3*Assumptions!$B$5 -> 1.2528
A4: Messages per business per month (count, not currency) | B4: =Assumptions!B8*Assumptions!B9*(1+Assumptions!B10) -> 1560
A5: AI cost per business per month | B5: =B4*B2 -> 1.8096 | C5: =B5*Assumptions!$B$5 -> 162.864
A6: AI cost per business per month under stress | B6: =B5*Assumptions!B11 -> 5.4288 | C6: =B6*Assumptions!$B$5 -> 488.592

Sheet Scale and margin
A1: Metric | B1: Prototype (1 business) | C1: 100 businesses | D1: 1,000 businesses
A2: Businesses | B2: 1 | C2: 100 | D2: 1000
A3: Messages per month | B3: =B2*'Usage and AI cost'!$B$4 -> 1560 | C3: =C2*'Usage and AI cost'!$B$4 -> 156000 | D3: =D2*'Usage and AI cost'!$B$4 -> 1560000
A4: AI cost per month (USD) | B4: =B2*'Usage and AI cost'!$B$5 -> 1.8096 | C4: =C2*'Usage and AI cost'!$B$5 -> 180.96 | D4: =D2*'Usage and AI cost'!$B$5 -> 1809.6
A5: Hosting and database per month (USD) | B5: 0 | C5: =Assumptions!$B$12 -> 45 | D5: =Assumptions!$B$13 -> 200
A6: Total cost per month (USD) | B6: =B4+B5 -> 1.8096 | C6: =C4+C5 -> 225.96 | D6: =D4+D5 -> 2009.6
A7: Total cost per business per month (USD) | B7: =B6/B2 -> 1.8096 | C7: =C6/C2 -> 2.2596 | D7: =D6/D2 -> 2.0096
A8: Total cost per business per month (INR) | B8: =B7*Assumptions!$B$5 -> 162.864 | C8: =C7*Assumptions!$B$5 -> 203.364 | D8: =D7*Assumptions!$B$5 -> 180.864
A9: Gross margin at the low price | B9: =(Assumptions!$B$14-B8)/Assumptions!$B$14 -> 0.67361924 | C9: =(Assumptions!$B$14-C8)/Assumptions!$B$14 -> 0.59245691 | D9: =(Assumptions!$B$14-D8)/Assumptions!$B$14 -> 0.63754709
A10: Gross margin at the high price | B10: =(Assumptions!$B$15-B8)/Assumptions!$B$15 -> 0.83697297 | C10: =(Assumptions!$B$15-C8)/Assumptions!$B$15 -> 0.79643243 | D10: =(Assumptions!$B$15-D8)/Assumptions!$B$15 -> 0.81895495
A11: Total cost per business under stress (INR) | B11: ='Usage and AI cost'!$C$6+B5/B2*Assumptions!$B$5 -> 488.592 | C11: ='Usage and AI cost'!$C$6+C5/C2*Assumptions!$B$5 -> 529.092 | D11: ='Usage and AI cost'!$C$6+D5/D2*Assumptions!$B$5 -> 506.592
A12: Gross margin under stress at the low price | B12: =(Assumptions!$B$14-B11)/Assumptions!$B$14 -> 0.020857715 | C12: =(Assumptions!$B$14-C11)/Assumptions!$B$14 -> -0.060304609 | D12: =(Assumptions!$B$14-D11)/Assumptions!$B$14 -> -0.015214429
A13: Gross margin under stress at the high price | B13: =(Assumptions!$B$15-B11)/Assumptions!$B$15 -> 0.51091892 | C13: =(Assumptions!$B$15-C11)/Assumptions!$B$15 -> 0.47037838 | D13: =(Assumptions!$B$15-D11)/Assumptions!$B$15 -> 0.4929009

Sheet Notes
A1: Note
A2: Pricing source: Google Gemini API pricing page (ai.google.dev/gemini-api/docs/pricing).
A3: Token usage is measured from one test conversation with two images, so it is on the heavy side; replace it with the averages from the full eval when available.
A4: The free tier is not used for the estimate: Google may use free-tier data to improve its models, so production needs a paid tier.
A5: WhatsApp messaging cost is near zero because Pakka only reads messages sent through the WhatsApp Business app.
A6: Excluded: Meta Tech Provider or partner fees, payment gateway fees, support and staff costs, and tax.
A7: To verify before submission: exchange rate, Vercel and Supabase prices.
A8: The model sits behind a one-line config change, so a different model can be costed by editing rows 1 to 3 and the token averages (Assumptions rows 2 to 4 and 6 to 7).
